{
    "bgee": {
    "authInfo": {
      "uuid": "",
      "priority": "chow-usr-01",
      "username": "bgee",
      "secureKey": "YXV0aD0weCxiZ2VlLHBsdXM="
    },
    "accVariables": {
      "chowBalance": 0,
      "pin": 1234
    },
    "accInfo": {
      "firstName": "Korede",
      "middleName": "Ayomide",
      "lastName": "Oluwole",
      "matricNo": "LCU/UG/22/13760",
      "emailAddr": "koyoyo@gmail.com",
      "nxtFunding": ""
    }
  },
  "beekay": {
    "authInfo": {
      "uuid": "",
      "priority": "chow-usr-01",
      "username": "beekay",
      "secureKey": "YXV0aD0weCxiZWVrYXksbWVkaWEyNg=="
    },
    "accVariables": {
      "chowBalance": 0,
      "pin": 1234
    },
    "accInfo": {
      "firstName": "Olamide",
      "middleName": "Caleb",
      "lastName": "Adeniyi",
      "matricNo": "LCU/UG/22/13924",
      "emailAddr": "calebmide@gmail.com",
      "nxtFunding": ""
    }
  },
    "dips": {
    "authInfo": {
      "uuid": "",
      "priority": "chow-usr-01",
      "username": "dips",
      "secureKey": "YXV0aD0weCxkaXBzLGJhYmVz"
    },
    "accVariables": {
      "chowBalance": 0,
      "pin": 1234
    },
    "accInfo": {
      "firstName": "Emmanuel",
      "middleName": "Oladayo",
      "lastName": "Adebayo",
      "matricNo": "LCU/UG/22/17331",
      "emailAddr": "dayobayo@gmail.com",
      "nxtFunding": ""
    }
  }
}
